advert_cafe/__init__.py
advert_cafe/main.py
advert_cafe-0.1.2.dist-info/METADATA
advert_cafe-0.1.2.dist-info/WHEEL
advert_cafe-0.1.2.dist-info/RECORD
